{
    "header": [{
        "type": "menuHeader",
        "content": "Ustawienia aplikacji"
    }],
    "sideMenuContent": [{
        "type": "menuContent",
        "content": {
            "Plansza": [
                ["Pokaż osie", "Zmaina opisu pól"],
                ["action.togAxis()", "print('generator menu')"]
            ],
            "Rysowanie": [
                ["Symetria - oś X", "Symetria - oś Y", "Zawartość pól"],
                ["action.symX()", "action.symY()", "print('generator menu')"]
            ]
        }
    }],
    "footer": [{
        "type": "menuFooter",
        "content": "<https://mzmix.github.io/>(Strona Główna)"
    }]
}